spooled/__init__.py
spooled/async_client.py
spooled/client.py
spooled/config.py
spooled/errors.py
spooled/py.typed
spooled/grpc/__init__.py
spooled/grpc/client.py
spooled/realtime/__init__.py
spooled/realtime/events.py
spooled/realtime/sse.py
spooled/realtime/unified.py
spooled/realtime/websocket.py
spooled/resources/__init__.py
spooled/resources/admin.py
spooled/resources/api_keys.py
spooled/resources/auth.py
spooled/resources/base.py
spooled/resources/billing.py
spooled/resources/dashboard.py
spooled/resources/health.py
spooled/resources/ingest.py
spooled/resources/jobs.py
spooled/resources/metrics.py
spooled/resources/organizations.py
spooled/resources/queues.py
spooled/resources/schedules.py
spooled/resources/webhooks.py
spooled/resources/workers.py
spooled/resources/workflows.py
spooled/types/__init__.py
spooled/types/admin.py
spooled/types/api_keys.py
spooled/types/auth.py
spooled/types/billing.py
spooled/types/common.py
spooled/types/dashboard.py
spooled/types/health.py
spooled/types/jobs.py
spooled/types/organizations.py
spooled/types/queues.py
spooled/types/schedules.py
spooled/types/webhooks.py
spooled/types/workers.py
spooled/types/workflows.py
spooled/utils/__init__.py
spooled/utils/async_http.py
spooled/utils/casing.py
spooled/utils/circuit_breaker.py
spooled/utils/http.py
spooled/utils/retry.py
spooled/worker/__init__.py
spooled/worker/async_worker.py
spooled/worker/types.py
spooled/worker/worker.py
spooled-1.0.12.dist-info/METADATA
spooled-1.0.12.dist-info/WHEEL
spooled-1.0.12.dist-info/licenses/LICENSE
spooled-1.0.12.dist-info/RECORD
