Metadata-Version: 2.4
Name: spooled
Version: 1.0.12
Summary: Official Python SDK for Spooled Cloud job queue service
Project-URL: Homepage, https://spooled.cloud
Project-URL: Documentation, https://spooled.cloud/docs/
Project-URL: Repository, https://github.com/spooled-cloud/spooled-sdk-python
Project-URL: Changelog, https://github.com/spooled-cloud/spooled-sdk-python/blob/main/CHANGELOG.md
Author-email: Spooled Cloud <support@spooled.cloud>
License-Expression: Apache-2.0
License-File: LICENSE
Keywords: background-jobs,cron,job-queue,scheduler,spooled,task-queue,webhooks,workflow
Classifier: Development Status :: 5 - Production/Stable
Classifier: Intended Audience :: Developers
Classifier: License :: OSI Approved :: Apache Software License
Classifier: Operating System :: OS Independent
Classifier: Programming Language :: Python :: 3
Classifier: Programming Language :: Python :: 3.10
Classifier: Programming Language :: Python :: 3.11
Classifier: Programming Language :: Python :: 3.12
Classifier: Typing :: Typed
Requires-Python: >=3.10
Requires-Dist: httpx>=0.25.0
Requires-Dist: pydantic>=2.0.0
Provides-Extra: all
Requires-Dist: grpcio-tools>=1.60.0; extra == 'all'
Requires-Dist: grpcio>=1.60.0; extra == 'all'
Requires-Dist: protobuf>=4.25.0; extra == 'all'
Requires-Dist: sseclient-py>=1.8.0; extra == 'all'
Requires-Dist: websockets>=12.0; extra == 'all'
Provides-Extra: dev
Requires-Dist: mypy>=1.8.0; extra == 'dev'
Requires-Dist: pre-commit>=3.6.0; extra == 'dev'
Requires-Dist: pytest-asyncio>=0.23.0; extra == 'dev'
Requires-Dist: pytest-cov>=4.1.0; extra == 'dev'
Requires-Dist: pytest>=7.4.0; extra == 'dev'
Requires-Dist: respx>=0.21.0; extra == 'dev'
Requires-Dist: ruff>=0.1.0; extra == 'dev'
Provides-Extra: grpc
Requires-Dist: grpcio-tools>=1.60.0; extra == 'grpc'
Requires-Dist: grpcio>=1.60.0; extra == 'grpc'
Requires-Dist: protobuf>=4.25.0; extra == 'grpc'
Provides-Extra: realtime
Requires-Dist: sseclient-py>=1.8.0; extra == 'realtime'
Requires-Dist: websockets>=12.0; extra == 'realtime'
Provides-Extra: worker
